rupture/__init__.py
rupture/rupture.py
rupture/utils/__init__.py
rupture/utils/six.py
rupture-1.4.5.dist-info/DESCRIPTION.rst
rupture-1.4.5.dist-info/METADATA
rupture-1.4.5.dist-info/RECORD
rupture-1.4.5.dist-info/WHEEL
rupture-1.4.5.dist-info/metadata.json
rupture-1.4.5.dist-info/top_level.txt
