Metadata-Version: 2.0
Name: rupture
Version: 1.4.5
Summary: A simple wrapper from requests and beautifulsoup.
Home-page: http://readthedocs.org/
Author: Shinz Natkid
Author-email: shinznatkid@gmail.com
License: UNKNOWN
Platform: UNKNOWN
Classifier: Development Status :: 5 - Production/Stable
Classifier: Environment :: Console
Classifier: Environment :: Web Environment
Classifier: Intended Audience :: Developers
Classifier: Intended Audience :: System Administrators
Classifier: License :: OSI Approved :: MIT License
Classifier: Operating System :: MacOS :: MacOS X
Classifier: Operating System :: Microsoft
Classifier: Operating System :: POSIX
Classifier: Programming Language :: Python
Classifier: Topic :: Internet :: WWW/HTTP
Classifier: Topic :: Internet :: WWW/HTTP :: Dynamic Content
Requires-Dist: beautifulsoup4 (>=4.0.0)
Requires-Dist: requests (>=1.0.0)
